nqrduck_autotm/__init__.py
nqrduck_autotm/autotm.py
nqrduck_autotm/controller.py
nqrduck_autotm/model.py
nqrduck_autotm/view.py
nqrduck_autotm/widget.py
nqrduck_autotm/resources/AutoTM.ini
nqrduck_autotm/resources/autotm_widget.ui
nqrduck_autotm-0.0.4.dist-info/METADATA
nqrduck_autotm-0.0.4.dist-info/WHEEL
nqrduck_autotm-0.0.4.dist-info/entry_points.txt
nqrduck_autotm-0.0.4.dist-info/licenses/LICENSE
nqrduck_autotm-0.0.4.dist-info/RECORD
