Metadata-Version: 2.3
Name: nqrduck-autotm
Version: 0.0.4
Summary: A module for the NQRduck program (a simple python script™) for automatic Tuning and Matching (TM) system used for magnetic resonance spectroscopy.
Project-URL: Homepage, https://nqrduck.cool
Project-URL: Bug Tracker, https://github.com/nqrduck/nqrduck-autotm/issues
Project-URL: Source Code, https://github.com/nqrduck/nqrduck-autotm
Author-email: jupfi <support@nqrduck.cool>
License: MIT License
License-File: LICENSE
Classifier: License :: OSI Approved :: MIT License
Classifier: Operating System :: OS Independent
Classifier: Programming Language :: Python :: 3
Requires-Python: >=3.10
Requires-Dist: matplotlib
Requires-Dist: nqrduck
Requires-Dist: pyqt6
Requires-Dist: pyserial
Requires-Dist: scipy
